{
  "db_name": "SQLite",
  "query": "select * from users where id = ?",
  "describe": {
    "columns": [
      {
        "name": "id",
        "ordinal": 0,
        "type_info": "Int64"
      },
      {
        "name": "login_code",
        "ordinal": 1,
        "type_info": "Text"
      },
      {
        "name": "created_at",
        "ordinal": 2,
        "type_info": "Int64"
      },
      {
        "name": "updated_at",
        "ordinal": 3,
        "type_info": "Int64"
      }
    ],
    "parameters": {
      "Right": 1
    },
    "nullable": [
      false,
      false,
      false,
      false
    ]
  },
  "hash": "94237023eee8e902d29a0a31c88be20e2ce46e76e052a5eefadfa252cc382247"
}